README.md
setup.py
src/upgradegit/__init__.py
src/upgradegit/cli.py
src/upgradegit.egg-info/PKG-INFO
src/upgradegit.egg-info/SOURCES.txt
src/upgradegit.egg-info/dependency_links.txt
src/upgradegit.egg-info/entry_points.txt
src/upgradegit.egg-info/not-zip-safe
src/upgradegit.egg-info/requires.txt
src/upgradegit.egg-info/top_level.txt